README.md
setup.cfg
setup.py
sqlno/__init__.py
sqlno.egg-info/PKG-INFO
sqlno.egg-info/SOURCES.txt
sqlno.egg-info/dependency_links.txt
sqlno.egg-info/requires.txt
sqlno.egg-info/top_level.txt
sqlno/athena/__init__.py
sqlno/athena/functions.py
sqlno/common/__init__.py
sqlno/common/aliases.py
sqlno/common/clauses.py
sqlno/common/expressions.py
sqlno/common/functions.py
sqlno/common/statements.py
sqlno/common/structures.py
sqlno/mysql/__init__.py
sqlno/mysql/clauses.py
sqlno/mysql/statements.py
sqlno/tests/__init__.py
sqlno/tests/athena/__init__.py
sqlno/tests/mysql/__init__.py
sqlno/tests/mysql/test_mysql.py